revolve2_standards-1.2.4.dist-info/RECORD
revolve2_standards-1.2.4.dist-info/WHEEL
revolve2_standards-1.2.4.dist-info/METADATA
revolve2/standards/planar_robot_representation.py
revolve2/standards/morphological_measures.py
revolve2/standards/modular_robots_v2.py
revolve2/standards/terrains.py
revolve2/standards/__init__.py
revolve2/standards/fitness_functions.py
revolve2/standards/py.typed
revolve2/standards/simulation_parameters.py
revolve2/standards/modular_robots_v1.py
revolve2/standards/interactive_objects/_ball.py
revolve2/standards/interactive_objects/__init__.py
revolve2/standards/ci_lab_utilities/_ip_camera.py
revolve2/standards/ci_lab_utilities/__init__.py
revolve2/standards/ci_lab_utilities/_calibrate_camera.py
revolve2/standards/morphological_novelty_metric/__init__.py
revolve2/standards/morphological_novelty_metric/_build_cmodule.py
revolve2/standards/morphological_novelty_metric/calculate_novelty.pyi
revolve2/standards/morphological_novelty_metric/calculate_novelty.cpython-310-darwin.so
revolve2/standards/morphological_novelty_metric/_coordinate_operations.py
revolve2/standards/morphological_novelty_metric/_morphological_novelty_metric.py
revolve2/standards/morphological_novelty_metric/_calculate_novelty.pyx
revolve2/standards/genotypes/__init__.py
revolve2/standards/genotypes/cppnwin/__init__.py
revolve2/standards/genotypes/cppnwin/_multineat_genotype_pickle_wrapper.py
revolve2/standards/genotypes/cppnwin/_random_multineat_genotype.py
revolve2/standards/genotypes/cppnwin/_multineat_rng_from_random.py
revolve2/standards/genotypes/cppnwin/modular_robot/_brain_genotype_cpg_orm.py
revolve2/standards/genotypes/cppnwin/modular_robot/__init__.py
revolve2/standards/genotypes/cppnwin/modular_robot/_multineat_params.py
revolve2/standards/genotypes/cppnwin/modular_robot/_brain_genotype_cpg.py
revolve2/standards/genotypes/cppnwin/modular_robot/_brain_cpg_network_neighbor.py
revolve2/standards/genotypes/cppnwin/modular_robot/v1/_body_genotype_orm_v1.py
revolve2/standards/genotypes/cppnwin/modular_robot/v1/_body_genotype_v1.py
